azure/__init__.py
azure/cli/__init__.py
azure/cli/command_modules/__init__.py
azure/cli/command_modules/storage/__init__.py
azure/cli/command_modules/storage/_client_factory.py
azure/cli/command_modules/storage/_format.py
azure/cli/command_modules/storage/_help.py
azure/cli/command_modules/storage/_params.py
azure/cli/command_modules/storage/_transformers.py
azure/cli/command_modules/storage/_validators.py
azure/cli/command_modules/storage/commands.py
azure/cli/command_modules/storage/completers.py
azure/cli/command_modules/storage/oauth_token_util.py
azure/cli/command_modules/storage/sdkutil.py
azure/cli/command_modules/storage/services_wrapper.py
azure/cli/command_modules/storage/storage_url_helpers.py
azure/cli/command_modules/storage/url_quote_util.py
azure/cli/command_modules/storage/util.py
azure/cli/command_modules/storage/azcopy/__init__.py
azure/cli/command_modules/storage/azcopy/util.py
azure/cli/command_modules/storage/operations/__init__.py
azure/cli/command_modules/storage/operations/account.py
azure/cli/command_modules/storage/operations/acl.py
azure/cli/command_modules/storage/operations/azcopy.py
azure/cli/command_modules/storage/operations/blob.py
azure/cli/command_modules/storage/operations/cors.py
azure/cli/command_modules/storage/operations/directory.py
azure/cli/command_modules/storage/operations/file.py
azure/cli/command_modules/storage/operations/logging.py
azure/cli/command_modules/storage/operations/metrics.py
azure/cli/command_modules/storage/operations/table.py
opal_azure_cli_storage-2.4.6.dist-info/METADATA
opal_azure_cli_storage-2.4.6.dist-info/WHEEL
opal_azure_cli_storage-2.4.6.dist-info/top_level.txt
opal_azure_cli_storage-2.4.6.dist-info/RECORD
